p3_data/__init__.py
p3_data/p3_common_lib.py
p3_data-2.0.2.dist-info/LICENSE
p3_data-2.0.2.dist-info/METADATA
p3_data-2.0.2.dist-info/WHEEL
p3_data-2.0.2.dist-info/top_level.txt
p3_data-2.0.2.dist-info/zip-safe
p3_data-2.0.2.dist-info/RECORD
