Metadata-Version: 2.1
Name: p3-data
Version: 2.0.2
Summary: A variety of utility functions to analyze results data produced by the P3 Test Driver.
Home-page: http://github.com/pravega/p3_test_driver
Author: Claudio Fahey
Author-email: claudio.fahey@dell.com
License: UNKNOWN
Platform: UNKNOWN
Classifier: License :: OSI Approved :: Apache Software License
Classifier: Operating System :: OS Independent
Classifier: Programming Language :: Python :: 3
Requires-Dist: IPython
Requires-Dist: ipywidgets
Requires-Dist: pandas
Requires-Dist: PyYaml
Requires-Dist: matplotlib
Requires-Dist: numpy
Requires-Dist: scipy
Requires-Dist: six
Requires-Dist: sklearn
